xmipp3_installer/__init__.py
xmipp3_installer/__main__.py
xmipp3_installer/api_client/api_client.py
xmipp3_installer/api_client/assembler/installation_info_assembler.py
xmipp3_installer/application/__init__.py
xmipp3_installer/application/user_interactions.py
xmipp3_installer/application/cli/__init__.py
xmipp3_installer/application/cli/cli.py
xmipp3_installer/application/cli/arguments/__init__.py
xmipp3_installer/application/cli/arguments/modes.py
xmipp3_installer/application/cli/arguments/params.py
xmipp3_installer/application/cli/parsers/base_help_formatter.py
xmipp3_installer/application/cli/parsers/error_handler_parser.py
xmipp3_installer/application/cli/parsers/format.py
xmipp3_installer/application/cli/parsers/general_help_formatter.py
xmipp3_installer/application/cli/parsers/mode_help_formatter.py
xmipp3_installer/application/logger/__init__.py
xmipp3_installer/application/logger/errors.py
xmipp3_installer/application/logger/logger.py
xmipp3_installer/application/logger/predefined_messages.py
xmipp3_installer/installer/__init__.py
xmipp3_installer/installer/installer_service.py
xmipp3_installer/installer/orquestrator.py
xmipp3_installer/installer/urls.py
xmipp3_installer/installer/constants/__init__.py
xmipp3_installer/installer/constants/paths.py
xmipp3_installer/installer/handlers/__init__.py
xmipp3_installer/installer/handlers/conda_handler.py
xmipp3_installer/installer/handlers/generic_package_handler.py
xmipp3_installer/installer/handlers/git_handler.py
xmipp3_installer/installer/handlers/shell_handler.py
xmipp3_installer/installer/handlers/versions_manager.py
xmipp3_installer/installer/handlers/cmake/__init__.py
xmipp3_installer/installer/handlers/cmake/cmake_constants.py
xmipp3_installer/installer/handlers/cmake/cmake_handler.py
xmipp3_installer/installer/modes/__init__.py
xmipp3_installer/installer/modes/mode_all_executor.py
xmipp3_installer/installer/modes/mode_config_executor.py
xmipp3_installer/installer/modes/mode_executor.py
xmipp3_installer-2.0.4.dist-info/licenses/LICENSE.txt
xmipp3_installer-2.0.4.dist-info/METADATA
xmipp3_installer-2.0.4.dist-info/WHEEL
xmipp3_installer-2.0.4.dist-info/entry_points.txt
xmipp3_installer-2.0.4.dist-info/top_level.txt
xmipp3_installer-2.0.4.dist-info/RECORD
