Metadata-Version: 2.4
Name: xmipp3-installer
Version: 2.0.4
Summary: Package to handle the installation of Xmipp3
Author-email: Martín Salinas <ssalinasmartin@gmail.com>
License: GPL-3.0-only
Project-URL: Homepage, https://github.com/I2PC/xmipp3-installer
Project-URL: Issues, https://github.com/I2PC/xmipp3-installer/issues
Keywords: xmipp3,installer
Classifier: Programming Language :: Python :: 3
Classifier: Programming Language :: Python :: 3.8
Classifier: Programming Language :: Python :: 3.9
Classifier: Programming Language :: Python :: 3.10
Classifier: Programming Language :: Python :: 3.11
Classifier: Programming Language :: Python :: 3.12
Classifier: Programming Language :: Python :: 3.13
Classifier: Programming Language :: Python :: 3.14
Classifier: Operating System :: POSIX :: Linux
Requires-Python: >=3.8
License-File: LICENSE.txt
Requires-Dist: typing-extensions>=4.12
Requires-Dist: distro>=1.8.0
Provides-Extra: test
Requires-Dist: pytest==8.*; python_version < "3.10" and extra == "test"
Requires-Dist: pytest==9.*; python_version >= "3.10" and extra == "test"
Requires-Dist: pytest-cov==5.*; python_version < "3.9" and extra == "test"
Requires-Dist: pytest-cov==7.*; python_version >= "3.9" and extra == "test"
Requires-Dist: pytest-subprocess==1.*; extra == "test"
Requires-Dist: pytest-localserver==0.*; extra == "test"
Requires-Dist: ruff==0.*; extra == "test"
Requires-Dist: cmake==4.*; extra == "test"
Requires-Dist: ninja==1.*; extra == "test"
Dynamic: license-file
